Workbook

Sheet Raw Data
A1: 💰 Personal Finance Tracker — Transaction Log
A2: Date | B2: Month | C2: Category | D2: Sub-Category | E2: Description | F2: Type | G2: Amount (₹)
A3: 2025-01-05 | B3: January | C3: Income | D3: Salary | E3: Monthly Salary | F3: Income | G3: 65000
A4: 2025-01-08 | B4: January | C4: Income | D4: Freelance | E4: Web Design Project | F4: Income | G4: 12000
A5: 2025-01-10 | B5: January | C5: Housing | D5: Rent | E5: House Rent January | F5: Expense | G5: 15000
A6: 2025-01-12 | B6: January | C6: Food | D6: Groceries | E6: Big Bazaar Monthly Shopping | F6: Expense | G6: 4500
A7: 2025-01-14 | B7: January | C7: Transport | D7: Fuel | E7: Petrol for Bike | F7: Expense | G7: 1200
A8: 2025-01-15 | B8: January | C8: Utilities | D8: Electricity | E8: EB Bill January | F8: Expense | G8: 850
A9: 2025-01-16 | B9: January | C9: Food | D9: Dining Out | E9: Family Dinner - Hotel | F9: Expense | G9: 1800
A10: 2025-01-18 | B10: January | C10: Entertainment | D10: OTT | E10: Netflix + Hotstar | F10: Expense | G10: 649
A11: 2025-01-20 | B11: January | C11: Healthcare | D11: Medicine | E11: Monthly Medicines | F11: Expense | G11: 560
A12: 2025-01-22 | B12: January | C12: Education | D12: Books | E12: Online Course - SQL | F12: Expense | G12: 1999
A13: 2025-01-25 | B13: January | C13: Savings | D13: FD | E13: Fixed Deposit | F13: Savings | G13: 10000
A14: 2025-01-28 | B14: January | C14: Utilities | D14: Mobile | E14: Jio Recharge | F14: Expense | G14: 299
... A40: 2025-03-28 | B40: March | C40: Utilities | D40: Mobile | E40: Jio Recharge | F40: Expense | G40: 299

Sheet Monthly Summary
A1: 📊 Monthly Income vs Expense vs Savings Summary
A2: Month | B2: Total Income (₹) | C2: Total Expense (₹) | D2: Total Savings (₹) | E2: Net Balance (₹) | F2: Savings Rate % | G2: Status
A3: January | B3: =SUMIFS('Raw Data'!G:G,'Raw Data'!B:B,A3,'Raw Data'!F:F,"Income") -> 77000 | C3: =SUMIFS('Raw Data'!G:G,'Raw Data'!B:B,A3,'Raw Data'!F:F,"Expense") -> 28057 | D3: =SUMIFS('Raw Data'!G:G,'Raw Data'!B:B,A3,'Raw Data'!F:F,"Savings") -> 10000 | E3: =B3-C3-D3 -> 38943 | F3: =IFERROR(D3/B3,0) -> 0.12987013 | G3: =IF(E3>0,"✅ Surplus",IF(E3=0,"⚖️ Break Even","❌ Deficit")) -> ✅ Surplus
A4: February | B4: =SUMIFS('Raw Data'!G:G,'Raw Data'!B:B,A4,'Raw Data'!F:F,"Income") -> 70000 | C4: =SUMIFS('Raw Data'!G:G,'Raw Data'!B:B,A4,'Raw Data'!F:F,"Expense") -> 29369 | D4: =SUMIFS('Raw Data'!G:G,'Raw Data'!B:B,A4,'Raw Data'!F:F,"Savings") -> 10000 | E4: =B4-C4-D4 -> 30631 | F4: =IFERROR(D4/B4,0) -> 0.14285714 | G4: =IF(E4>0,"✅ Surplus",IF(E4=0,"⚖️ Break Even","❌ Deficit")) -> ✅ Surplus
A5: March | B5: =SUMIFS('Raw Data'!G:G,'Raw Data'!B:B,A5,'Raw Data'!F:F,"Income") -> 85000 | C5: =SUMIFS('Raw Data'!G:G,'Raw Data'!B:B,A5,'Raw Data'!F:F,"Expense") -> 31478 | D5: =SUMIFS('Raw Data'!G:G,'Raw Data'!B:B,A5,'Raw Data'!F:F,"Savings") -> 15000 | E5: =B5-C5-D5 -> 38522 | F5: =IFERROR(D5/B5,0) -> 0.17647059 | G5: =IF(E5>0,"✅ Surplus",IF(E5=0,"⚖️ Break Even","❌ Deficit")) -> ✅ Surplus
A6: TOTAL / AVERAGE | B6: =SUM(B3:B5) -> 232000 | C6: =SUM(C3:C5) -> 88904 | D6: =SUM(D3:D5) -> 35000 | E6: =SUM(E3:E5) -> 108096 | F6: =AVERAGE(F3:F5) -> 0.14973262 | G6: =IF(E6>0,"✅ Surplus","❌ Deficit") -> ✅ Surplus

Sheet Category Breakdown
A1: 🏷️ Expense Breakdown by Category
A2: Category | B2: Description | C2: Jan (₹) | D2: Feb (₹) | E2: Mar (₹) | F2: Total (₹) | G2: % of Expense
A3: Housing | B3: Rent & Maintenance | C3: =SUMIFS('Raw Data'!G:G,'Raw Data'!B:B,"January",'Raw Data'!C:C,A3,'Raw Data'!F:F,"Expense") -> 15000 | D3: =SUMIFS('Raw Data'!G:G,'Raw Data'!B:B,"February",'Raw Data'!C:C,A3,'Raw Data'!F:F,"Expense") -> 15000 | E3: =SUMIFS('Raw Data'!G:G,'Raw Data'!B:B,"March",'Raw Data'!C:C,A3,'Raw Data'!F:F,"Expense") -> 15000 | F3: =SUM(C3:E3) -> 45000 | G3: =IFERROR(F3/F11,0) -> 0.50616395
A4: Food | B4: Groceries & Dining | C4: =SUMIFS('Raw Data'!G:G,'Raw Data'!B:B,"January",'Raw Data'!C:C,A4,'Raw Data'!F:F,"Expense") -> 7500 | D4: =SUMIFS('Raw Data'!G:G,'Raw Data'!B:B,"February",'Raw Data'!C:C,A4,'Raw Data'!F:F,"Expense") -> 6150 | E4: =SUMIFS('Raw Data'!G:G,'Raw Data'!B:B,"March",'Raw Data'!C:C,A4,'Raw Data'!F:F,"Expense") -> 7000 | F4: =SUM(C4:E4) -> 20650 | G4: =IFERROR(F4/F11,0) -> 0.23227301
A5: Transport | B5: Fuel, Auto, Cab | C5: =SUMIFS('Raw Data'!G:G,'Raw Data'!B:B,"January",'Raw Data'!C:C,A5,'Raw Data'!F:F,"Expense") -> 1200 | D5: =SUMIFS('Raw Data'!G:G,'Raw Data'!B:B,"February",'Raw Data'!C:C,A5,'Raw Data'!F:F,"Expense") -> 1800 | E5: =SUMIFS('Raw Data'!G:G,'Raw Data'!B:B,"March",'Raw Data'!C:C,A5,'Raw Data'!F:F,"Expense") -> 1400 | F5: =SUM(C5:E5) -> 4400 | G5: =IFERROR(F5/F11,0) -> 0.049491586
A6: Utilities | B6: Electricity, Mobile | C6: =SUMIFS('Raw Data'!G:G,'Raw Data'!B:B,"January",'Raw Data'!C:C,A6,'Raw Data'!F:F,"Expense") -> 1149 | D6: =SUMIFS('Raw Data'!G:G,'Raw Data'!B:B,"February",'Raw Data'!C:C,A6,'Raw Data'!F:F,"Expense") -> 1219 | E6: =SUMIFS('Raw Data'!G:G,'Raw Data'!B:B,"March",'Raw Data'!C:C,A6,'Raw Data'!F:F,"Expense") -> 1079 | F6: =SUM(C6:E6) -> 3447 | G6: =IFERROR(F6/F11,0) -> 0.038772159
A7: Entertainment | B7: Movies, OTT, Travel | C7: =SUMIFS('Raw Data'!G:G,'Raw Data'!B:B,"January",'Raw Data'!C:C,A7,'Raw Data'!F:F,"Expense") -> 649 | D7: =SUMIFS('Raw Data'!G:G,'Raw Data'!B:B,"February",'Raw Data'!C:C,A7,'Raw Data'!F:F,"Expense") -> 1200 | E7: =SUMIFS('Raw Data'!G:G,'Raw Data'!B:B,"March",'Raw Data'!C:C,A7,'Raw Data'!F:F,"Expense") -> 5500 | F7: =SUM(C7:E7) -> 7349 | G7: =IFERROR(F7/F11,0) -> 0.082662197
A8: Healthcare | B8: Doctor & Medicine | C8: =SUMIFS('Raw Data'!G:G,'Raw Data'!B:B,"January",'Raw Data'!C:C,A8,'Raw Data'!F:F,"Expense") -> 560 | D8: =SUMIFS('Raw Data'!G:G,'Raw Data'!B:B,"February",'Raw Data'!C:C,A8,'Raw Data'!F:F,"Expense") -> 500 | E8: =SUMIFS('Raw Data'!G:G,'Raw Data'!B:B,"March",'Raw Data'!C:C,A8,'Raw Data'!F:F,"Expense") -> 800 | F8: =SUM(C8:E8) -> 1860 | G8: =IFERROR(F8/F11,0) -> 0.020921443
A9: Education | B9: Books & Courses | C9: =SUMIFS('Raw Data'!G:G,'Raw Data'!B:B,"January",'Raw Data'!C:C,A9,'Raw Data'!F:F,"Expense") -> 1999 | D9: =SUMIFS('Raw Data'!G:G,'Raw Data'!B:B,"February",'Raw Data'!C:C,A9,'Raw Data'!F:F,"Expense") -> 0 | E9: =SUMIFS('Raw Data'!G:G,'Raw Data'!B:B,"March",'Raw Data'!C:C,A9,'Raw Data'!F:F,"Expense") -> 699 | F9: =SUM(C9:E9) -> 2698 | G9: =IFERROR(F9/F11,0) -> 0.030347341
A10: Clothing | B10: Apparel & Accessories | C10: =SUMIFS('Raw Data'!G:G,'Raw Data'!B:B,"January",'Raw Data'!C:C,A10,'Raw Data'!F:F,"Expense") -> 0 | D10: =SUMIFS('Raw Data'!G:G,'Raw Data'!B:B,"February",'Raw Data'!C:C,A10,'Raw Data'!F:F,"Expense") -> 3500 | E10: =SUMIFS('Raw Data'!G:G,'Raw Data'!B:B,"March",'Raw Data'!C:C,A10,'Raw Data'!F:F,"Expense") -> 0 | F10: =SUM(C10:E10) -> 3500 | G10: =IFERROR(F10/F11,0) -> 0.039368307
A11: TOTAL | B11: All Expense Categories | C11: =SUM(C3:C10) -> 28057 | D11: =SUM(D3:D10) -> 29369 | E11: =SUM(E3:E10) -> 31478 | F11: =SUM(F3:F10) -> 88904 | G11: =SUM(G3:G10) -> 1

Sheet Dashboard
A1: 💼 Personal Finance Dashboard — Q1 2025
A2: Auto-calculated from Raw Data | Update the Raw Data sheet to refresh all numbers
A4: Total Income | D4: Total Expenses | G4: Total Savings | J4: Avg Savings Rate
A5: =SUM('Monthly Summary'!B3:B5) -> 232000 | D5: =SUM('Monthly Summary'!C3:C5) -> 88904 | G5: =SUM('Monthly Summary'!D3:D5) -> 35000 | J5: =AVERAGE('Monthly Summary'!F3:F5) -> 0.14973262
A9: NET BALANCE (Q1 2025)
A10: =SUM('Monthly Summary'!E3:E5) -> 108096
A11: =IF(A10>0,"✅ You are on track! Keep saving consistently.",IF(A10=0,"⚖️ Break Even — Try to increase savings.","❌ Overspent! Review your expenses immediately.")) -> ✅ You are on track! Keep saving consistently.
A13: 📋 Quick Statistics
A14: Highest Income Month | D14: =INDEX('Monthly Summary'!A3:A5,MATCH(MAX('Monthly Summary'!B3:B5),'Monthly Summary'!B3:B5,0)) -> March
A15: Highest Expense Month | D15: =INDEX('Monthly Summary'!A3:A5,MATCH(MAX('Monthly Summary'!C3:C5),'Monthly Summary'!C3:C5,0)) -> March
A16: Best Savings Month | D16: =INDEX('Monthly Summary'!A3:A5,MATCH(MAX('Monthly Summary'!D3:D5),'Monthly Summary'!D3:D5,0)) -> March
A17: Avg Monthly Income | D17: =AVERAGE('Monthly Summary'!B3:B5) -> 77333.333
A18: Avg Monthly Expense | D18: =AVERAGE('Monthly Summary'!C3:C5) -> 29634.667
A19: Top Expense Category | D19: =INDEX('Category Breakdown'!A3:A10,MATCH(MAX('Category Breakdown'!F3:F10),'Category Breakdown'!F3:F10,0)) -> Housing

Sheet README
A1: 📘 GitHub README — How to Use This Project
A2: PROJECT NAME: | B2: Personal Finance Tracker — MS Excel
A3: AUTHOR: | B3: Your Name (update this)
A4: SKILLS DEMONSTRATED: | B4: MS Excel: Formulas, Pivot, Charts, Conditional Formatting, Cross-Sheet References
A6: SHEET GUIDE:
A7: Raw Data | B7: → Enter all your transactions here. One row per transaction.
A8: Monthly Summary | B8: → Auto-calculates Income, Expense, Savings per month. Has a bar chart.
A9: Category Breakdown | B9: → Shows where your money goes. Has a pie chart.
A10: Dashboard | B10: → KPI cards and summary stats. The main view to share.
A12: HOW TO ADD DATA:
A13: Step 1 | B13: Go to the 'Raw Data' sheet
A14: Step 2 | B14: Add a new row with: Date, Month, Category, Sub-Category, Description, Type, Amount
A15: Step 3 | B15: Type must be exactly: Income / Expense / Savings (case-sensitive)
A16: Step 4 | B16: All other sheets update automatically!
A18: EXCEL FORMULAS USED:
A19: SUMIFS | B19: SUMIFS(range, criteria_range, criteria, ...) — Sums with multiple conditions
A20: IFERROR | B20: IFERROR(formula, value_if_error) — Handles division by zero gracefully
A21: INDEX+MATCH | B21: INDEX(array, MATCH(lookup, range, 0)) — Flexible two-way lookup
A22: IF Nested | B22: IF(condition, value_if_true, IF(...)) — Multi-condition logic branching
A24: GITHUB UPLOAD GUIDE:
A25: Step 1 | B25: Create repo: github.com → New Repository → Name: 'personal-finance-tracker-excel'
A26: Step 2 | B26: Upload this .xlsx file and any screenshots to the repo
A27: Step 3 | B27: Create a README.md with project description and screenshot
A28: Step 4 | B28: Add topics: excel, data-analysis, finance, personal-finance
